alo/__init__.py
alo/__version__.py
alo/alo.py
alo/constants.py
alo/exceptions.py
alo/logger.py
alo/main.py
alo/model.py
alo/solution_register.py
alo/utils.py
alo/yml_schema.py
alo/ConfigFormats/aws_codebuild_buildspec_format.yaml
alo/ConfigFormats/aws_codebuild_s3_project_format.json
alo/ConfigFormats/experimental_plan.yaml
alo/ConfigFormats/experimental_plan_format.yaml
alo/Dockerfiles/SagemakerDockerfile
alo/Dockerfiles/main.py
alo/Dockerfiles/requirements.txt
alo/Dockerfiles/register/InferenceDockerfile
alo/Dockerfiles/register/Makefile
alo/Dockerfiles/register/TrainDockerfile
alo/config/ai_conductor_api.json
alo/config/redis_error_table.json
setting/infra_config.yaml
setting/sagemaker_config.yaml
setting/solution_info.yaml
setting/example_infra_config/infra_config.aic.meerkat_dev.yaml
setting/example_infra_config/infra_config.aic.meerkat_edu.yaml
setting/example_infra_config/infra_config.aictest.yaml
setting/example_infra_config/infra_config.customer.yaml
setting/example_infra_config/infra_config.lgebigdata.yaml
setting/example_infra_config/infra_config.localtest.yaml
setting/example_infra_config/infra_config.magna.yaml
setting/example_infra_config/infra_config.solution.storage.yaml
solution/experimental_plan.yaml
solution/titanic.py
solution/inference/result.csv
solution/inference/dataset/test.csv
solution/inference/models/n100_depth5.pkl
solution/train/dataset/train.csv
template/experimental_plan.yaml
template/inference_dataset.csv
template/titanic.py
template/train_dataset.csv
template/setting/infra_config.yaml
template/setting/sagemaker_config.yaml
template/setting/solution_info.yaml
template/setting/example_infra_config/infra_config.aic.meerkat_dev.yaml
template/setting/example_infra_config/infra_config.aic.meerkat_edu.yaml
template/setting/example_infra_config/infra_config.aictest.yaml
template/setting/example_infra_config/infra_config.customer.yaml
template/setting/example_infra_config/infra_config.lgebigdata.yaml
mellarikat_alo-3.0.dist-info/METADATA
mellarikat_alo-3.0.dist-info/WHEEL
mellarikat_alo-3.0.dist-info/entry_points.txt
mellarikat_alo-3.0.dist-info/top_level.txt
mellarikat_alo-3.0.dist-info/RECORD
